pyLiveKML/__init__.py
pyLiveKML/errors.py
pyLiveKML/utils.py
pyLiveKML/objects/AbstractView.py
pyLiveKML/objects/AnimatedUpdate.py
pyLiveKML/objects/BalloonStyle.py
pyLiveKML/objects/Camera.py
pyLiveKML/objects/ColorStyle.py
pyLiveKML/objects/Container.py
pyLiveKML/objects/Document.py
pyLiveKML/objects/ExtendedData.py
pyLiveKML/objects/Feature.py
pyLiveKML/objects/FlyTo.py
pyLiveKML/objects/Folder.py
pyLiveKML/objects/Geometry.py
pyLiveKML/objects/GroundOverlay.py
pyLiveKML/objects/Icon.py
pyLiveKML/objects/IconStyle.py
pyLiveKML/objects/LabelStyle.py
pyLiveKML/objects/LineString.py
pyLiveKML/objects/LineStyle.py
pyLiveKML/objects/LinearRing.py
pyLiveKML/objects/Link.py
pyLiveKML/objects/ListStyle.py
pyLiveKML/objects/LookAt.py
pyLiveKML/objects/Model.py
pyLiveKML/objects/MultiGeometry.py
pyLiveKML/objects/MultiTrack.py
pyLiveKML/objects/NetworkLink.py
pyLiveKML/objects/NetworkLinkControl.py
pyLiveKML/objects/Object.py
pyLiveKML/objects/Overlay.py
pyLiveKML/objects/PhotoOverlay.py
pyLiveKML/objects/Placemark.py
pyLiveKML/objects/Point.py
pyLiveKML/objects/PolyStyle.py
pyLiveKML/objects/Polygon.py
pyLiveKML/objects/Region.py
pyLiveKML/objects/Schema.py
pyLiveKML/objects/ScreenOverlay.py
pyLiveKML/objects/SoundCue.py
pyLiveKML/objects/Style.py
pyLiveKML/objects/StyleMap.py
pyLiveKML/objects/StyleSelector.py
pyLiveKML/objects/SubStyle.py
pyLiveKML/objects/TimePrimitive.py
pyLiveKML/objects/TimeSpan.py
pyLiveKML/objects/TimeStamp.py
pyLiveKML/objects/Tour.py
pyLiveKML/objects/TourControl.py
pyLiveKML/objects/TourPrimitive.py
pyLiveKML/objects/Track.py
pyLiveKML/objects/Update.py
pyLiveKML/objects/Wait.py
pyLiveKML/objects/__init__.py
pyLiveKML/types/GeoColor.py
pyLiveKML/types/GeoCoordinates.py
pyLiveKML/types/Vec2.py
pyLiveKML/types/__init__.py
pyLiveKML/types/types.py
pylivekml-1.1.1.dist-info/licenses/LICENCE
pylivekml-1.1.1.dist-info/METADATA
pylivekml-1.1.1.dist-info/WHEEL
pylivekml-1.1.1.dist-info/top_level.txt
pylivekml-1.1.1.dist-info/RECORD
