Metadata-Version: 2.4
Name: pyLiveKML
Version: 1.1.1
Summary: A pure-Python library for live-streaming KML content to Google Earth Pro.
Author-email: smoke-you <smoke-you@nonexistent.com>
License-Expression: AGPL-3.0-or-later
Project-URL: Homepage, https://github.com/smoke-you/pyLiveKML
Project-URL: Issues, https://github.com/smoke-you/pyLiveKML/issues
Classifier: Programming Language :: Python :: 3
Classifier: Operating System :: OS Independent
Requires-Python: >=3.10
License-File: LICENCE
Requires-Dist: lxml>=6.0.0
Requires-Dist: python-dateutil
Dynamic: license-file
